[
  {
    "id": "2",
    "fName": "Jane",
    "lName": "Doe",
    "email": "jane.doe@example.com",
    "notes": "Another sample contact",
    "createdAt": "2024-02-18T08:47:49.487Z",
    "updatedAt": "2024-02-18T19:35:06.467Z"
  },
  {
    "id": "id-1708051767029",
    "fName": "Kane",
    "lName": "Dann",
    "email": "kanedanny@gmail.com",
    "notes": "",
    "createdAt": "2024-02-16T04:18:14.876Z",
    "updatedAt": "2024-02-16T04:18:14.877Z"
  },
  {
    "id": "id-1708320569418",
    "fName": "Krish",
    "lName": "ms",
    "email": "krishkrishnan2001@gmail.com",
    "notes": "saxd",
    "createdAt": "2024-02-19T05:29:29.418Z",
    "updatedAt": "2024-02-19T05:29:29.418Z"
  },
  {
    "id": "generated-id-1708369569414",
    "fName": "Theepan",
    "lName": "Gandhi",
    "email": "theepgan@mail.com",
    "notes": "Hey Buddy, Whats up!",
    "createdAt": "2024-02-19T19:06:09.414Z",
    "updatedAt": "2024-02-19T19:06:09.414Z"
  }
]